pychai/__init__.py
pychai/objects.py
pychai/presets.py
pychai/pychai.py
pychai/tools.py
pychai/topology.yaml
pychai/ui.py
pychai/wen.yaml
pychai/zi.yaml
pychai/preset/__init__.py
pychai/preset/fingertip.py
pychai/preset/fingertip.schema.yaml
pychai/preset/wubi86.schema.yaml
pychai/preset/wubi98.py
pychai/preset/wubi98.schema.yaml
pychai/preset/xiaoqing.py
pychai/preset/xiaoqing.schema.yaml
pychai-1.0.1.dist-info/LICENSE
pychai-1.0.1.dist-info/METADATA
pychai-1.0.1.dist-info/WHEEL
pychai-1.0.1.dist-info/top_level.txt
pychai-1.0.1.dist-info/RECORD
