Metadata-Version: 2.1
Name: pychai
Version: 1.0.1
Summary: A System for Automatic Chinese Character Decomposition
Home-page: https://github.com/lanluoxiao/Chai
Author: Luoxiao Lan
Author-email: 2320693692@qq.com
License: UNKNOWN
Platform: UNKNOWN
Classifier: Programming Language :: Python :: 3
Classifier: License :: OSI Approved :: GNU General Public License v3 (GPLv3)
Classifier: Operating System :: OS Independent
Requires-Python: >=3.6
Requires-Dist: PyYAML
